{
  "kind": "collectionType",
  "collectionName": "static_programms",
  "info": {
    "singularName": "static-programm",
    "pluralName": "static-programms",
    "displayName": "StaticProgramms",
    "description": ""
  },
  "options": {
    "draftAndPublish": true
  },
  "pluginOptions": {
    "i18n": {
      "localized": true
    }
  },
  "attributes": {
    "title": {
      "type": "text",
      "pluginOptions": {
        "i18n": {
          "localized": true
        }
      }
    },
    "more": {
      "type": "text",
      "pluginOptions": {
        "i18n": {
          "localized": true
        }
      }
    }
  }
}
